Metadata-Version: 2.1
Name: rams
Version: 0.0.1
Summary: A brief description of your package
Home-page: https://github.com/yourusername/your_package_name
Author: kumar
Author-email: your.email@example.com
Classifier: Development Status :: 3 - Alpha
Classifier: Intended Audience :: Developers
Classifier: License :: OSI Approved :: MIT License
Classifier: Programming Language :: Python :: 3
Classifier: Programming Language :: Python :: 3.6
Classifier: Programming Language :: Python :: 3.7
Classifier: Programming Language :: Python :: 3.8
